pandahouse/__init__.py
pandahouse/convert.py
pandahouse/core.py
pandahouse/http.py
pandahouse/utils.py
intelecy_pandahouse-0.4.1.dist-info/LICENSE
intelecy_pandahouse-0.4.1.dist-info/WHEEL
intelecy_pandahouse-0.4.1.dist-info/METADATA
intelecy_pandahouse-0.4.1.dist-info/RECORD
