Metadata-Version: 2.1
Name: intelecy-pandahouse
Version: 0.4.1
Summary: Pandas interface for Clickhouse HTTP API
Home-page: https://github.com/Intelecy/pandahouse
License: BSD-3-Clause
Author: Krisztián Szűcs
Author-email: szucs.krisztian@gmail.com
Requires-Python: >=3.8.0,<4.0.0
Classifier: License :: OSI Approved :: BSD License
Classifier: Programming Language :: Python :: 3
Classifier: Programming Language :: Python :: 3.10
Classifier: Programming Language :: Python :: 3.8
Classifier: Programming Language :: Python :: 3.9
Requires-Dist: pandas (>=1.4.3)
Requires-Dist: requests (>=2.28.1)
Requires-Dist: toolz (>=0.12.0)
Project-URL: Repository, https://github.com/Intelecy/pandahouse
